DependencyConfusion
