Metadata-Version: 2.1
Name: DependencyConfusion
Version: 666
Summary: This package implements a test for Dependency Confusion using pip.
Home-page: https://github.com/mauricelambert/DependencyConfusion
Author: Maurice Lambert
Author-email: mauricelambert434@gmail.com
Maintainer: Maurice Lambert
Maintainer-email: mauricelambert434@gmail.com
License: GPL-3.0 License
Keywords: DependencyConfusion,Dependency,Confusion,Vulnerability,POC,pip,packages,CVE
Platform: Windows
Platform: Linux
Platform: MacOS
Classifier: Programming Language :: Python
Classifier: Development Status :: 5 - Production/Stable
Classifier: Topic :: Security
Classifier: Natural Language :: English
Classifier: Programming Language :: Python :: 3.9
Classifier: Operating System :: POSIX :: Linux
Classifier: Operating System :: Microsoft :: Windows
Classifier: Operating System :: MacOS
Requires-Python: >=3.6
